aci/__init__.py
aci/aci.py
aci/utils/__init__.py
aci/utils/amplicon_splitting.py
aci/utils/divide_chrom_by_span.py
aci/utils/genome_depth.py
aci/utils/get_amplicon_counts.py
aci/utils/get_coverage.py
aci/utils/get_paired_read_positions.py
aci/utils/get_unpaired_read_positions.py
aci/utils/group_create.py
aci/utils/group_mean.py
aci/utils/is_paired.py
aci/utils/load_bed_intervals.py
aci/utils/parse_args.py
aci/utils/plotting_amplicons.py
aci/utils/plotting_boxplot.py
aci/utils/plotting_depth.py
aci/utils/prep.py
aci/utils/process_bams_in_parallel.py
aci/utils/read_and_assign.py
aci/utils/split_dataframe.py
amplicon_coverage_inspector-1.15.250702.dist-info/licenses/LICENSE
amplicon_coverage_inspector-1.15.250702.dist-info/METADATA
amplicon_coverage_inspector-1.15.250702.dist-info/WHEEL
amplicon_coverage_inspector-1.15.250702.dist-info/entry_points.txt
amplicon_coverage_inspector-1.15.250702.dist-info/top_level.txt
amplicon_coverage_inspector-1.15.250702.dist-info/RECORD
