Metadata-Version: 2.4
Name: amplicon_coverage_inspector
Version: 1.15.250702
Summary: Visualization of coverage for amplicon sequencing
Author-email: Erin Young <eriny@utah.gov>
License: MIT
Project-URL: Source, https://github.com/erinyoung/ACI
Keywords: bioinformatics,amplicon,coverage,visualization
Classifier: Programming Language :: Python :: 3
Classifier: Development Status :: 4 - Beta
Classifier: Intended Audience :: Science/Research
Classifier: Intended Audience :: Developers
Classifier: License :: OSI Approved :: MIT License
Classifier: Topic :: Scientific/Engineering :: Bio-Informatics
Requires-Python: <4,>=3.8
License-File: LICENSE
Requires-Dist: pandas
Requires-Dist: pysam
Requires-Dist: matplotlib
Requires-Dist: numpy
Requires-Dist: intervaltree
Dynamic: license-file
